odoo/addons/stock_request_purchase_analytic/README.rst
odoo/addons/stock_request_purchase_analytic/__init__.py
odoo/addons/stock_request_purchase_analytic/__manifest__.py
odoo/addons/stock_request_purchase_analytic/i18n/stock_request_purchase_analytic.pot
odoo/addons/stock_request_purchase_analytic/models/__init__.py
odoo/addons/stock_request_purchase_analytic/models/procurement_rule.py
odoo/addons/stock_request_purchase_analytic/static/description/icon.png
odoo/addons/stock_request_purchase_analytic/tests/__init__.py
odoo/addons/stock_request_purchase_analytic/tests/test_stock_request_purchase_analytic.py
odoo11_addon_stock_request_purchase_analytic-11.0.1.0.2.dist-info/METADATA
odoo11_addon_stock_request_purchase_analytic-11.0.1.0.2.dist-info/WHEEL
odoo11_addon_stock_request_purchase_analytic-11.0.1.0.2.dist-info/top_level.txt
odoo11_addon_stock_request_purchase_analytic-11.0.1.0.2.dist-info/RECORD
